gitlab_depcheck/__init__.py
gitlab_depcheck/cli.py
gitlab_depcheck-0.5.4.dist-info/METADATA
gitlab_depcheck-0.5.4.dist-info/WHEEL
gitlab_depcheck-0.5.4.dist-info/entry_points.txt
gitlab_depcheck-0.5.4.dist-info/licenses/LICENSE
gitlab_depcheck-0.5.4.dist-info/RECORD
