Metadata-Version: 2.4
Name: gitlab-depcheck
Version: 0.5.4
Summary: Check python package dependencies across GitLab projects
Project-URL: Homepage, https://github.com/sesav/gitlab-depcheck
Project-URL: Repository, https://github.com/sesav/gitlab-depcheck
Project-URL: Issues, https://github.com/sesav/gitlab-gitlab-depcheck/issues
Author-email: Sergey Silaev <hello@8am.dev>
License: MIT
License-File: LICENSE
Keywords: checker,dependencies,gitlab,package,python,python310,python311,python312,python313
Classifier: Development Status :: 4 - Beta
Classifier: Intended Audience :: Developers
Classifier: License :: OSI Approved :: MIT License
Classifier: Programming Language :: Python
Classifier: Programming Language :: Python :: 3
Classifier: Programming Language :: Python :: 3.10
Classifier: Programming Language :: Python :: 3.11
Classifier: Programming Language :: Python :: 3.12
Classifier: Programming Language :: Python :: 3.13
Classifier: Programming Language :: Python :: 3.14
Classifier: Topic :: Software Development :: Libraries :: Python Modules
Classifier: Topic :: Utilities
Requires-Python: >=3.10
Requires-Dist: click>=8.3.1
Requires-Dist: httpx>=0.28.1
Requires-Dist: rich>=14.2.0
Requires-Dist: tomli>=2.3.0
